MANIFEST.in
setup.py
xagen37_fast_hist_conflict/fast_hist.py
xagen37_fast_hist_conflict.egg-info/PKG-INFO
xagen37_fast_hist_conflict.egg-info/SOURCES.txt
xagen37_fast_hist_conflict.egg-info/dependency_links.txt
xagen37_fast_hist_conflict.egg-info/requires.txt
xagen37_fast_hist_conflict.egg-info/top_level.txt