Metadata-Version: 1.0
Name: xagen37-fast-hist-conflict
Version: 0.2.0
Summary: Dummy module for doing lab.
Home-page: UNKNOWN
Author: Alexander Sofrygin
Author-email: xagen37@gmail.com
License: UNKNOWN
Platform: UNKNOWN
